maihem_poc/__init__.py
maihem_poc/core/__init__.py
maihem_poc/core/ai.py
maihem_poc/core/questions.py
maihem_poc/data/__init__.py
maihem_poc/data/db.py
maihem_poc/data/loader.py
maihem_poc/data/vectoriser.py
maihem_poc/metrics/__init__.py
maihem_poc-1.0.1.dist-info/LICENSE
maihem_poc-1.0.1.dist-info/METADATA
maihem_poc-1.0.1.dist-info/WHEEL
maihem_poc-1.0.1.dist-info/RECORD
